Metadata-Version: 1.0
Name: django-shop-simplecategories
Version: 0.0.5
Summary: A simple to use product categories module for django SHOP
Home-page: http://www.django-shop.org/
Author: Christopher Glass
Author-email: tribaal@gmail.com
License: BSD License
Platform: OS Independent
